kameleoon/__init__.py
kameleoon/defaults.py
kameleoon/exceptions.py
kameleoon/kameleoon_client.py
kameleoon/kameleoon_client_config.py
kameleoon/kameleoon_client_factory.py
kameleoon/middleware.py
kameleoon/sdk_version.py
kameleoon/client_readiness/__init__.py
kameleoon/client_readiness/async_readiness.py
kameleoon/client_readiness/threading_readiness.py
kameleoon/configuration/__init__.py
kameleoon/configuration/consent_blocking_behaviour.py
kameleoon/configuration/custom_data_info.py
kameleoon/configuration/data_file.py
kameleoon/configuration/experiment.py
kameleoon/configuration/feature_flag.py
kameleoon/configuration/me_group.py
kameleoon/configuration/rule.py
kameleoon/configuration/rule_type.py
kameleoon/configuration/settings.py
kameleoon/configuration/variable.py
kameleoon/configuration/variation.py
kameleoon/configuration/variation_by_exposition.py
kameleoon/data/__init__.py
kameleoon/data/browser.py
kameleoon/data/cbscores.py
kameleoon/data/conversion.py
kameleoon/data/cookie.py
kameleoon/data/custom_data.py
kameleoon/data/data.py
kameleoon/data/device.py
kameleoon/data/geolocation.py
kameleoon/data/kcs_heat.py
kameleoon/data/mapping_identifier.py
kameleoon/data/operating_system.py
kameleoon/data/page_view.py
kameleoon/data/personalization.py
kameleoon/data/targeted_segment.py
kameleoon/data/unique_identifier.py
kameleoon/data/user_agent.py
kameleoon/data/visitor_visits.py
kameleoon/data/manager/__init__.py
kameleoon/data/manager/assigned_variation.py
kameleoon/data/manager/forced_experiment_variation.py
kameleoon/data/manager/forced_feature_variation.py
kameleoon/data/manager/forced_variation.py
kameleoon/data/manager/legal_consent.py
kameleoon/data/manager/page_view_visit.py
kameleoon/data/manager/visitor.py
kameleoon/data/manager/visitor_manager.py
kameleoon/data/manager/visitor_slot.py
kameleoon/helpers/__init__.py
kameleoon/helpers/domain.py
kameleoon/helpers/functions.py
kameleoon/helpers/hasher.py
kameleoon/helpers/logger.py
kameleoon_client_python-3.17.1.dist-info/METADATA
kameleoon_client_python-3.17.1.dist-info/WHEEL
kameleoon_client_python-3.17.1.dist-info/top_level.txt
kameleoon_client_python-3.17.1.dist-info/RECORD
