Metadata-Version: 2.4
Name: kameleoon-client-python
Version: 3.17.1
Summary: Kameleoon Client Python Software Development Kit.
Home-page: https://developers.kameleoon.com/python-sdk.html
Author: Kameleoon
Author-email: sdk@kameleoon.com
License: GPLv3
Classifier: License :: OSI Approved :: GNU General Public License v3 (GPLv3)
Classifier: Programming Language :: Python
Classifier: Programming Language :: Python :: 3.8
Classifier: Programming Language :: Python :: 3.9
Classifier: Programming Language :: Python :: 3.10
Classifier: Programming Language :: Python :: Implementation :: CPython
Classifier: Programming Language :: Python :: Implementation :: PyPy
Requires-Python: >=3.8.0
Requires-Dist: pyyaml<6.1.0,>=5.4.0
Requires-Dist: requests<3.0.0,>=2.25
Requires-Dist: sseclient-py<1.9.0,>=1.7.0
Requires-Dist: aiohttp<4.0.0,>=3.8.0
Provides-Extra: test
Requires-Dist: flake8==4.0.1; extra == "test"
Requires-Dist: freezegun==1.1.0; extra == "test"
Requires-Dist: types-requests==2.25.0; extra == "test"
Requires-Dist: pytest-asyncio==0.21.*; extra == "test"
Requires-Dist: types-python-dateutil==2.8.2; extra == "test"
Requires-Dist: pytest-pythonpath==0.7.3; extra == "test"
Requires-Dist: aioresponses==0.7.*; extra == "test"
Requires-Dist: wheel==0.36.2; extra == "test"
Requires-Dist: requests<3.0.0,>=2.25; extra == "test"
Requires-Dist: twine==3.4.1; extra == "test"
Requires-Dist: pytest-django==4.4.0; extra == "test"
Requires-Dist: types-PyYAML==5.4.3; extra == "test"
Requires-Dist: pyyaml<6.1.0,>=5.4.0; extra == "test"
Requires-Dist: pytest-cov==2.12.1; extra == "test"
Requires-Dist: pytest-ordering==0.6; extra == "test"
Requires-Dist: sseclient-py<1.9.0,>=1.7.0; extra == "test"
Requires-Dist: Werkzeug==2.0.1; extra == "test"
Requires-Dist: pylint==2.12.*; extra == "test"
Requires-Dist: Django==3.2.4; extra == "test"
Requires-Dist: mypy==0.991; extra == "test"
Requires-Dist: aiohttp<4.0.0,>=3.8.0; extra == "test"
Dynamic: author
Dynamic: author-email
Dynamic: classifier
Dynamic: description
Dynamic: description-content-type
Dynamic: home-page
Dynamic: license
Dynamic: provides-extra
Dynamic: requires-dist
Dynamic: requires-python
Dynamic: summary
